[
  {
    "full_name": "pawelborkar/awesome-repos",
    "stargazers_count": 2923,
    "open_issues_count": 5,
    "forks_count": 256
  },
  {
    "full_name": "academind/react-native-practical-guide-code",
    "stargazers_count": 1627,
    "open_issues_count": 22,
    "forks_count": 1449
  },
  {
    "full_name": "tursodatabase/libsql",
    "stargazers_count": 15974,
    "open_issues_count": 407,
    "forks_count": 454
  },
  {
    "full_name": "shadcn-ui/ui",
    "stargazers_count": 103349,
    "open_issues_count": 1779,
    "forks_count": 7523
  },
  {
    "full_name": "zhao-stanley/chroma-ai",
    "stargazers_count": 201,
    "open_issues_count": 1,
    "forks_count": 7
  },
  {
    "full_name": "YurisCodingClub/zero-minds",
    "stargazers_count": 14,
    "open_issues_count": 0,
    "forks_count": 17
  },
  {
    "full_name": "Significant-Gravitas/AutoGPT",
    "stargazers_count": 180438,
    "open_issues_count": 290,
    "forks_count": 46192
  },
  {
    "full_name": "localsend/localsend",
    "stargazers_count": 72082,
    "open_issues_count": 841,
    "forks_count": 3859
  },
  {
    "full_name": "Frontesque/scrcpy-plus",
    "stargazers_count": 696,
    "open_issues_count": 19,
    "forks_count": 53
  },
  {
    "full_name": "volta-cli/volta",
    "stargazers_count": 12678,
    "open_issues_count": 331,
    "forks_count": 321
  },
  {
    "full_name": "facebook/sapling",
    "stargazers_count": 6663,
    "open_issues_count": 281,
    "forks_count": 328
  },
  {
    "full_name": "animate-css/animate.css",
    "stargazers_count": 82537,
    "open_issues_count": 73,
    "forks_count": 16132
  },
  {
    "full_name": "storybookjs/storybook",
    "stargazers_count": 88879,
    "open_issues_count": 2248,
    "forks_count": 9818
  },
  {
    "full_name": "TanStack/router",
    "stargazers_count": 12774,
    "open_issues_count": 473,
    "forks_count": 1421
  },
  {
    "full_name": "dailydotdev/daily",
    "stargazers_count": 19674,
    "open_issues_count": 39,
    "forks_count": 553
  },
  {
    "full_name": "ripienaar/free-for-dev",
    "stargazers_count": 116447,
    "open_issues_count": 13,
    "forks_count": 11893
  },
  {
    "full_name": "decaporg/decap-cms",
    "stargazers_count": 18766,
    "open_issues_count": 592,
    "forks_count": 3113
  },
  {
    "full_name": "falcon-Z/system-design-primer",
    "stargazers_count": 1,
    "open_issues_count": 0,
    "forks_count": 0
  },
  {
    "full_name": "falcon-Z/awesome-oss-alternatives",
    "stargazers_count": 1,
    "open_issues_count": 0,
    "forks_count": 0
  },
  {
    "full_name": "RunaCapital/awesome-oss-alternatives",
    "stargazers_count": 18507,
    "open_issues_count": 65,
    "forks_count": 988
  },
  {
    "full_name": "Ebazhanov/linkedin-skill-assessments-quizzes",
    "stargazers_count": 28661,
    "open_issues_count": 20,
    "forks_count": 13118
  },
  {
    "full_name": "trimstray/the-book-of-secret-knowledge",
    "stargazers_count": 199453,
    "open_issues_count": 102,
    "forks_count": 12160
  },
  {
    "full_name": "donnemartin/system-design-primer",
    "stargazers_count": 329985,
    "open_issues_count": 516,
    "forks_count": 53717
  },
  {
    "full_name": "beekeeper-studio/beekeeper-studio",
    "stargazers_count": 21529,
    "open_issues_count": 1002,
    "forks_count": 1395
  },
  {
    "full_name": "adesgautam/dj-angular",
    "stargazers_count": 75,
    "open_issues_count": 1,
    "forks_count": 57
  },
  {
    "full_name": "nvaccess/nvda",
    "stargazers_count": 2449,
    "open_issues_count": 2181,
    "forks_count": 734
  },
  {
    "full_name": "hyperledger-iroha/iroha-dco",
    "stargazers_count": 980,
    "open_issues_count": 18,
    "forks_count": 293
  }
]